[
  {
    "type": 0,
    "spellIcon": 3194610,
    "nodeID": 82552,
    "spellName": "Idol of N'Zoth",
    "maxRanks": 1,
    "spellID": 373280
  },
  {
    "type": 0,
    "spellIcon": 627685,
    "nodeID": 82553,
    "spellName": "Idol of Y'Shaarj",
    "maxRanks": 1,
    "spellID": 373310
  },
  {
    "deadTalent": 1
  },
  {
    "type": 0,
    "spellIcon": 298654,
    "nodeID": 82555,
    "spellName": "Idol of Yogg-Saron",
    "maxRanks": 1,
    "spellID": 373273
  },
  {
    "type": 0,
    "spellIcon": 614257,
    "nodeID": 82556,
    "spellName": "Phantasm",
    "maxRanks": 1,
    "spellID": 108942
  },
  {
    "type": 0,
    "spellIcon": 136201,
    "nodeID": 82557,
    "spellName": "Shadow Crash",
    "maxRanks": 1,
    "spellID": 205385
  },
  {
    "type": 2,
    "spellIcon": 136149,
    "nodeID": 82558,
    "spellName": "Deathspeaker",
    "maxRanks": 1,
    "spellID": 392507
  },
  {
    "type": 2,
    "spellIcon": 425954,
    "nodeID": 82558,
    "spellName": "Mind Flay: Insanity",
    "maxRanks": 1,
    "spellID": 391399
  },
  {
    "type": 0,
    "spellIcon": 237569,
    "nodeID": 82559,
    "spellName": "Mind Melt",
    "maxRanks": 1,
    "spellID": 391090
  },
  {
    "type": 0,
    "spellIcon": 425950,
    "nodeID": 82560,
    "spellName": "Insidious Ire",
    "maxRanks": 2,
    "spellID": 373212
  },
  {
    "type": 0,
    "spellIcon": 135740,
    "nodeID": 82561,
    "spellName": "Mind Devourer",
    "maxRanks": 2,
    "spellID": 373202
  },
  {
    "type": 0,
    "spellIcon": 136131,
    "nodeID": 82562,
    "spellName": "Encroaching Shadows",
    "maxRanks": 1,
    "spellID": 391235
  },
  {
    "type": 0,
    "spellIcon": 237298,
    "nodeID": 82563,
    "spellName": "Whispers of the Damned",
    "maxRanks": 2,
    "spellID": 391137
  },
  {
    "deadTalent": 1
  },
  {
    "deadTalent": 1
  },
  {
    "deadTalent": 1
  },
  {
    "deadTalent": 1
  },
  {
    "deadTalent": 1
  },
  {
    "deadTalent": 1
  },
  {
    "deadTalent": 1
  },
  {
    "deadTalent": 1
  },
  {
    "deadTalent": 1
  },
  {
    "deadTalent": 1
  },
  {
    "deadTalent": 1
  },
  {
    "deadTalent": 1
  },
  {
    "deadTalent": 1
  },
  {
    "deadTalent": 1
  },
  {
    "deadTalent": 1
  },
  {
    "deadTalent": 1
  },
  {
    "deadTalent": 1
  },
  {
    "deadTalent": 1
  },
  {
    "deadTalent": 1
  },
  {
    "deadTalent": 1
  },
  {
    "deadTalent": 1
  },
  {
    "deadTalent": 1
  },
  {
    "deadTalent": 1
  },
  {
    "deadTalent": 1
  },
  {
    "deadTalent": 1
  },
  {
    "deadTalent": 1
  },
  {
    "deadTalent": 1
  },
  {
    "deadTalent": 1
  },
  {
    "deadTalent": 1
  },
  {
    "deadTalent": 1
  },
  {
    "deadTalent": 1
  },
  {
    "deadTalent": 1
  },
  {
    "deadTalent": 1
  },
  {
    "deadTalent": 1
  },
  {
    "deadTalent": 1
  },
  {
    "deadTalent": 1
  },
  {
    "deadTalent": 1
  },
  {
    "deadTalent": 1
  },
  {
    "deadTalent": 1
  },
  {
    "deadTalent": 1
  },
  {
    "deadTalent": 1
  },
  {
    "deadTalent": 1
  },
  {
    "deadTalent": 1
  },
  {
    "deadTalent": 1
  },
  {
    "deadTalent": 1
  },
  {
    "deadTalent": 1
  },
  {
    "deadTalent": 1
  },
  {
    "deadTalent": 1
  },
  {
    "deadTalent": 1
  },
  {
    "deadTalent": 1
  },
  {
    "deadTalent": 1
  },
  {
    "deadTalent": 1
  },
  {
    "deadTalent": 1
  },
  {
    "deadTalent": 1
  },
  {
    "deadTalent": 1
  },
  {
    "deadTalent": 1
  },
  {
    "deadTalent": 1
  },
  {
    "deadTalent": 1
  },
  {
    "deadTalent": 1
  },
  {
    "deadTalent": 1
  },
  {
    "deadTalent": 1
  },
  {
    "deadTalent": 1
  },
  {
    "deadTalent": 1
  },
  {
    "deadTalent": 1
  },
  {
    "deadTalent": 1
  },
  {
    "deadTalent": 1
  },
  {
    "deadTalent": 1
  },
  {
    "deadTalent": 1
  },
  {
    "deadTalent": 1
  },
  {
    "deadTalent": 1
  },
  {
    "deadTalent": 1
  },
  {
    "deadTalent": 1
  },
  {
    "deadTalent": 1
  },
  {
    "deadTalent": 1
  },
  {
    "deadTalent": 1
  },
  {
    "deadTalent": 1
  },
  {
    "deadTalent": 1
  },
  {
    "deadTalent": 1
  },
  {
    "type": 0,
    "spellIcon": 236407,
    "nodeID": 82643,
    "spellName": "Idol of C'Thun",
    "maxRanks": 1,
    "spellID": 377349
  },
  {
    "type": 0,
    "spellIcon": 136130,
    "nodeID": 82644,
    "spellName": "Inescapable Torment",
    "maxRanks": 2,
    "spellID": 373427
  },
  {
    "type": 0,
    "spellIcon": 135978,
    "nodeID": 82645,
    "spellName": "Maddening Touch",
    "maxRanks": 2,
    "spellID": 391228
  },
  {
    "type": 0,
    "spellIcon": 132299,
    "nodeID": 82646,
    "spellName": "Puppet Master",
    "maxRanks": 1,
    "spellID": 377387
  },
  {
    "type": 0,
    "spellIcon": 332402,
    "nodeID": 82647,
    "spellName": "Harnessed Shadows",
    "maxRanks": 1,
    "spellID": 391296
  },
  {
    "type": 0,
    "spellIcon": 136214,
    "nodeID": 82648,
    "spellName": "Mindbender",
    "maxRanks": 1,
    "spellID": 200174
  },
  {
    "type": 0,
    "spellIcon": 136208,
    "nodeID": 82649,
    "spellName": "Screams of the Void",
    "maxRanks": 2,
    "spellID": 375767
  },
  {
    "type": 2,
    "spellIcon": 132291,
    "nodeID": 82650,
    "spellName": "Misery",
    "maxRanks": 1,
    "spellID": 238558
  },
  {
    "type": 2,
    "spellIcon": 132851,
    "nodeID": 82650,
    "spellName": "Dark Void",
    "maxRanks": 1,
    "spellID": 263346
  },
  {
    "type": 0,
    "spellIcon": 458230,
    "nodeID": 82651,
    "spellName": "Silence",
    "maxRanks": 1,
    "spellID": 15487
  },
  {
    "type": 2,
    "spellIcon": 458230,
    "nodeID": 82652,
    "spellName": "Last Word",
    "maxRanks": 1,
    "spellID": 263716
  },
  {
    "type": 2,
    "spellIcon": 237568,
    "nodeID": 82652,
    "spellName": "Psychic Horror",
    "maxRanks": 1,
    "spellID": 64044
  },
  {
    "type": 0,
    "spellIcon": 458969,
    "nodeID": 82653,
    "spellName": "Coalescing Shadows",
    "maxRanks": 1,
    "spellID": 391242
  },
  {
    "type": 2,
    "spellIcon": 236295,
    "nodeID": 82654,
    "spellName": "Damnation",
    "maxRanks": 1,
    "spellID": 341374
  },
  {
    "type": 2,
    "spellIcon": 1386551,
    "nodeID": 82654,
    "spellName": "Void Torrent",
    "maxRanks": 1,
    "spellID": 263165
  },
  {
    "type": 0,
    "spellIcon": 237557,
    "nodeID": 82655,
    "spellName": "Malediction",
    "maxRanks": 2,
    "spellID": 373221
  },
  {
    "type": 0,
    "spellIcon": 1386549,
    "nodeID": 82656,
    "spellName": "Ancient Madness",
    "maxRanks": 2,
    "spellID": 341240
  },
  {
    "type": 2,
    "spellIcon": 1445237,
    "nodeID": 82657,
    "spellName": "Dark Ascension",
    "maxRanks": 1,
    "spellID": 391109
  },
  {
    "type": 2,
    "spellIcon": 1386548,
    "nodeID": 82657,
    "spellName": "Void Eruption",
    "maxRanks": 1,
    "spellID": 228260
  },
  {
    "type": 0,
    "spellIcon": 1386547,
    "nodeID": 82658,
    "spellName": "Unfurling Darkness",
    "maxRanks": 1,
    "spellID": 341273
  },
  {
    "type": 2,
    "spellIcon": 237563,
    "nodeID": 82659,
    "spellName": "Intangibility",
    "maxRanks": 1,
    "spellID": 288733
  },
  {
    "type": 2,
    "spellIcon": 1022945,
    "nodeID": 82659,
    "spellName": "Mental Fortitude",
    "maxRanks": 1,
    "spellID": 377065
  },
  {
    "type": 0,
    "spellIcon": 610679,
    "nodeID": 82660,
    "spellName": "Dark Evangelism",
    "maxRanks": 2,
    "spellID": 391095
  },
  {
    "type": 0,
    "spellIcon": 878214,
    "nodeID": 82661,
    "spellName": "Mental Decay",
    "maxRanks": 1,
    "spellID": 375994
  },
  {
    "type": 0,
    "spellIcon": 136183,
    "nodeID": 82662,
    "spellName": "Shadowy Insight",
    "maxRanks": 1,
    "spellID": 375888
  },
  {
    "type": 0,
    "spellIcon": 237563,
    "nodeID": 82663,
    "spellName": "Dispersion",
    "maxRanks": 1,
    "spellID": 47585
  },
  {
    "type": 0,
    "spellIcon": 237565,
    "nodeID": 82664,
    "spellName": "Mind Sear",
    "maxRanks": 1,
    "spellID": 48045
  },
  {
    "type": 0,
    "spellIcon": 252997,
    "nodeID": 82665,
    "spellName": "Devouring Plague",
    "maxRanks": 1,
    "spellID": 335467
  },
  {
    "type": 0,
    "spellIcon": 458229,
    "nodeID": 82666,
    "spellName": "Shadowy Apparitions",
    "maxRanks": 1,
    "spellID": 341491
  },
  {
    "type": 2,
    "spellIcon": 1022944,
    "nodeID": 82667,
    "spellName": "Auspicious Spirits",
    "maxRanks": 1,
    "spellID": 155271
  },
  {
    "type": 2,
    "spellIcon": 237567,
    "nodeID": 82667,
    "spellName": "Tormented Spirits",
    "maxRanks": 1,
    "spellID": 391284
  },
  {
    "type": 0,
    "spellIcon": 457655,
    "nodeID": 82668,
    "spellName": "Mind Spike",
    "maxRanks": 1,
    "spellID": 73510
  },
  {
    "type": 0,
    "spellIcon": 633004,
    "nodeID": 82669,
    "spellName": "Surge of Darkness",
    "maxRanks": 1,
    "spellID": 162448
  },
  {
    "type": 0,
    "spellIcon": 1445238,
    "nodeID": 82670,
    "spellName": "Psychic Link",
    "maxRanks": 2,
    "spellID": 199484
  },
  {
    "type": 0,
    "spellIcon": 136143,
    "nodeID": 82671,
    "spellName": "Pain of Death",
    "maxRanks": 2,
    "spellID": 391288
  },
  {
    "type": 0,
    "spellIcon": 3565723,
    "nodeID": 82672,
    "spellName": "Manipulation",
    "maxRanks": 2,
    "spellID": 390996
  },
  {
    "type": 0,
    "spellIcon": 3528308,
    "nodeID": 82673,
    "spellName": "Shattered Perceptions",
    "maxRanks": 1,
    "spellID": 391112
  },
  {
    "type": 0,
    "spellIcon": 537079,
    "nodeID": 82674,
    "spellName": "Void Shift",
    "maxRanks": 1,
    "spellID": 108968
  },
  {
    "type": 0,
    "spellIcon": 633042,
    "nodeID": 82675,
    "spellName": "Angelic Bulwark",
    "maxRanks": 1,
    "spellID": 108945
  },
  {
    "type": 0,
    "spellIcon": 4667420,
    "nodeID": 82676,
    "spellName": "Power Word: Life",
    "maxRanks": 1,
    "spellID": 373481
  },
  {
    "type": 0,
    "spellIcon": 135981,
    "nodeID": 82677,
    "spellName": "Surge of Light",
    "maxRanks": 2,
    "spellID": 109186
  },
  {
    "type": 2,
    "spellIcon": 237550,
    "nodeID": 82678,
    "spellName": "Angel's Mercy",
    "maxRanks": 1,
    "spellID": 238100
  },
  {
    "type": 2,
    "spellIcon": 135883,
    "nodeID": 82678,
    "spellName": "Binding Heals",
    "maxRanks": 1,
    "spellID": 368275
  },
  {
    "type": 0,
    "spellIcon": 135954,
    "nodeID": 82679,
    "spellName": "Light's Inspiration",
    "maxRanks": 2,
    "spellID": 373450
  },
  {
    "type": 2,
    "spellIcon": 631519,
    "nodeID": 82680,
    "spellName": "Divine Star",
    "maxRanks": 1,
    "spellID": 122121
  },
  {
    "type": 2,
    "spellIcon": 632353,
    "nodeID": 82680,
    "spellName": "Halo",
    "maxRanks": 1,
    "spellID": 120644
  },
  {
    "type": 0,
    "spellIcon": 458412,
    "nodeID": 82681,
    "spellName": "Crystalline Reflection",
    "maxRanks": 2,
    "spellID": 373457
  },
  {
    "deadTalent": 1
  },
  {
    "type": 0,
    "spellIcon": 2175503,
    "nodeID": 82683,
    "spellName": "Twins of the Sun Priestess",
    "maxRanks": 1,
    "spellID": 373466
  },
  {
    "type": 0,
    "spellIcon": 237566,
    "nodeID": 82684,
    "spellName": "Twist of Fate",
    "maxRanks": 2,
    "spellID": 390972
  },
  {
    "type": 0,
    "spellIcon": 136047,
    "nodeID": 82685,
    "spellName": "Translucent Image",
    "maxRanks": 1,
    "spellID": 373446
  },
  {
    "type": 0,
    "spellIcon": 135994,
    "nodeID": 82686,
    "spellName": "Improved Fade",
    "maxRanks": 2,
    "spellID": 390670
  },
  {
    "type": 0,
    "spellIcon": 3565723,
    "nodeID": 82687,
    "spellName": "Mindgames",
    "maxRanks": 1,
    "spellID": 375901
  },
  {
    "type": 0,
    "spellIcon": 3163621,
    "nodeID": 82688,
    "spellName": "Tithe Evasion",
    "maxRanks": 1,
    "spellID": 373223
  },
  {
    "type": 0,
    "spellIcon": 132299,
    "nodeID": 82689,
    "spellName": "Apathy",
    "maxRanks": 1,
    "spellID": 390668
  },
  {
    "type": 0,
    "spellIcon": 343633,
    "nodeID": 82690,
    "spellName": "San'layn",
    "maxRanks": 1,
    "spellID": 199855
  },
  {
    "type": 0,
    "spellIcon": 136230,
    "nodeID": 82691,
    "spellName": "Vampiric Embrace",
    "maxRanks": 1,
    "spellID": 15286
  },
  {
    "type": 0,
    "spellIcon": 132886,
    "nodeID": 82692,
    "spellName": "Void Shield",
    "maxRanks": 1,
    "spellID": 280749
  },
  {
    "type": 0,
    "spellIcon": 136091,
    "nodeID": 82693,
    "spellName": "Shackle Undead",
    "maxRanks": 1,
    "spellID": 9484
  },
  {
    "type": 0,
    "spellIcon": 135939,
    "nodeID": 82694,
    "spellName": "Power Infusion",
    "maxRanks": 1,
    "spellID": 10060
  },
  {
    "type": 0,
    "spellIcon": 132339,
    "nodeID": 82695,
    "spellName": "Psychic Voice",
    "maxRanks": 1,
    "spellID": 196704
  },
  {
    "type": 0,
    "spellIcon": 135928,
    "nodeID": 82696,
    "spellName": "Inspiration",
    "maxRanks": 1,
    "spellID": 390676
  },
  {
    "type": 0,
    "spellIcon": 236317,
    "nodeID": 82697,
    "spellName": "Unwavering Will",
    "maxRanks": 2,
    "spellID": 373456
  },
  {
    "type": 0,
    "spellIcon": 135739,
    "nodeID": 82698,
    "spellName": "Improved Mass Dispel",
    "maxRanks": 1,
    "spellID": 341167
  },
  {
    "type": 0,
    "spellIcon": 135739,
    "nodeID": 82699,
    "spellName": "Mass Dispel",
    "maxRanks": 1,
    "spellID": 32375
  },
  {
    "type": 0,
    "spellIcon": 135922,
    "nodeID": 82700,
    "spellName": "Rhapsody",
    "maxRanks": 1,
    "spellID": 390622
  },
  {
    "type": 0,
    "spellIcon": 135922,
    "nodeID": 82701,
    "spellName": "Holy Nova",
    "maxRanks": 1,
    "spellID": 132157
  },
  {
    "type": 0,
    "spellIcon": 1022949,
    "nodeID": 82702,
    "spellName": "Move with Grace",
    "maxRanks": 1,
    "spellID": 390620
  },
  {
    "type": 0,
    "spellIcon": 642580,
    "nodeID": 82703,
    "spellName": "Angelic Feather",
    "maxRanks": 1,
    "spellID": 121536
  },
  {
    "type": 0,
    "spellIcon": 135935,
    "nodeID": 82704,
    "spellName": "Purify Disease",
    "maxRanks": 1,
    "spellID": 213634
  },
  {
    "deadTalent": 1
  },
  {
    "type": 0,
    "spellIcon": 135982,
    "nodeID": 82706,
    "spellName": "Body and Soul",
    "maxRanks": 1,
    "spellID": 64129
  },
  {
    "type": 2,
    "spellIcon": 135923,
    "nodeID": 82707,
    "spellName": "Protective Light",
    "maxRanks": 1,
    "spellID": 193063
  },
  {
    "type": 2,
    "spellIcon": 135907,
    "nodeID": 82707,
    "spellName": "From Darkness Comes Light",
    "maxRanks": 1,
    "spellID": 390615
  },
  {
    "type": 2,
    "spellIcon": 3163624,
    "nodeID": 82708,
    "spellName": "Sheer Terror",
    "maxRanks": 1,
    "spellID": 390919
  },
  {
    "type": 2,
    "spellIcon": 537022,
    "nodeID": 82708,
    "spellName": "Void Tendrils",
    "maxRanks": 1,
    "spellID": 108920
  },
  {
    "type": 0,
    "spellIcon": 136163,
    "nodeID": 82709,
    "spellName": "Throes of Pain",
    "maxRanks": 2,
    "spellID": 377422
  },
  {
    "type": 2,
    "spellIcon": 136206,
    "nodeID": 82710,
    "spellName": "Mind Control",
    "maxRanks": 1,
    "spellID": 605
  },
  {
    "type": 2,
    "spellIcon": 1386549,
    "nodeID": 82710,
    "spellName": "Dominate Mind",
    "maxRanks": 1,
    "spellID": 205364
  },
  {
    "type": 0,
    "spellIcon": 136149,
    "nodeID": 82711,
    "spellName": "Death and Madness",
    "maxRanks": 1,
    "spellID": 321291
  },
  {
    "type": 0,
    "spellIcon": 136149,
    "nodeID": 82712,
    "spellName": "Shadow Word: Death",
    "maxRanks": 1,
    "spellID": 32379
  },
  {
    "type": 0,
    "spellIcon": 136214,
    "nodeID": 82713,
    "spellName": "Shadowfiend",
    "maxRanks": 1,
    "spellID": 34433
  },
  {
    "type": 0,
    "spellIcon": 135915,
    "nodeID": 82714,
    "spellName": "Improved Flash Heal",
    "maxRanks": 1,
    "spellID": 393870
  },
  {
    "type": 0,
    "spellIcon": 136066,
    "nodeID": 82715,
    "spellName": "Dispel Magic",
    "maxRanks": 1,
    "spellID": 528
  },
  {
    "type": 0,
    "spellIcon": 463835,
    "nodeID": 82716,
    "spellName": "Leap of Faith",
    "maxRanks": 1,
    "spellID": 73325
  },
  {
    "type": 0,
    "spellIcon": 135953,
    "nodeID": 82717,
    "spellName": "Renew",
    "maxRanks": 1,
    "spellID": 139
  },
  {
    "type": 0,
    "spellIcon": 135944,
    "nodeID": 82718,
    "spellName": "Prayer of Mending",
    "maxRanks": 1,
    "spellID": 33076
  },
  {
    "type": 0,
    "spellIcon": 236372,
    "nodeID": 82719,
    "spellName": "Focused Mending",
    "maxRanks": 1,
    "spellID": 372354
  },
  {
    "type": 2,
    "spellIcon": 135976,
    "nodeID": 82720,
    "spellName": "Spell Warding",
    "maxRanks": 1,
    "spellID": 390667
  },
  {
    "type": 2,
    "spellIcon": 135877,
    "nodeID": 82720,
    "spellName": "Blessed Recovery",
    "maxRanks": 1,
    "spellID": 390767
  },
  {
    "type": 0,
    "spellIcon": 1022947,
    "nodeID": 82721,
    "spellName": "Words of the Pious",
    "maxRanks": 1,
    "spellID": 377438
  },
  {
    "deadTalent": 1
  },
  {
    "deadTalent": 1
  }
]